CHANGELOG.txt
LICENSE.txt
MANIFEST.in
README.md
setup.py
adder/__init__.py
arunsundaram.egg-info/PKG-INFO
arunsundaram.egg-info/SOURCES.txt
arunsundaram.egg-info/dependency_links.txt
arunsundaram.egg-info/top_level.txt